main.py
project_templates-0.0.1.dist-info/LICENCE
project_templates-0.0.1.dist-info/METADATA
project_templates-0.0.1.dist-info/WHEEL
project_templates-0.0.1.dist-info/top_level.txt
project_templates-0.0.1.dist-info/RECORD
