Metadata-Version: 2.1
Name: project_templates
Version: 0.0.1
Summary: Pre-set basic templates of common Python projects
Project-URL: Homepage, https://github.com/pedrohgoncalvess/basic-project-templates
Requires-Python: >=3.10
License-File: LICENCE
Requires-Dist: altgraph==0.17.4
Requires-Dist: importlib_metadata==8.5.0
Requires-Dist: packaging==24.2
Requires-Dist: pefile==2023.2.7
Requires-Dist: pyaml==24.12.0
Requires-Dist: pyinstaller==6.11.1
Requires-Dist: pyinstaller-hooks-contrib==2024.10
Requires-Dist: python-dotenv==1.0.1
Requires-Dist: pywin32-ctypes==0.2.3
Requires-Dist: PyYAML==6.0.2
Requires-Dist: sqlparse==0.5.3
Requires-Dist: tabulate==0.9.0
Requires-Dist: yoyo-migrations==9.0.0
Requires-Dist: zipp==3.21.0
